README
setup.py
autoresponse/__init__.py
autoresponse.egg-info/PKG-INFO
autoresponse.egg-info/SOURCES.txt
autoresponse.egg-info/dependency_links.txt
autoresponse.egg-info/requires.txt
autoresponse.egg-info/top_level.txt